MANIFEST.in
Makefile
README
mangler.py
setup.cfg
setup.py
tiddlywebconfig.py
test/__init__.py
test/__init__.pyc
test/test_post_validate.py
test/__pycache__/test_post_validate.cpython-27-PYTEST.pyc
tiddlywebplugins/__init__.py
tiddlywebplugins/csrf.py
tiddlywebplugins.csrf.egg-info/PKG-INFO
tiddlywebplugins.csrf.egg-info/SOURCES.txt
tiddlywebplugins.csrf.egg-info/dependency_links.txt
tiddlywebplugins.csrf.egg-info/namespace_packages.txt
tiddlywebplugins.csrf.egg-info/not-zip-safe
tiddlywebplugins.csrf.egg-info/requires.txt
tiddlywebplugins.csrf.egg-info/top_level.txt