Metadata-Version: 1.0
Name: tiddlywebplugins.csrf
Version: 0.5.1
Summary: CSRF Middleware Protector for TiddlyWeb
Home-page: http://pypi.python.org/pypi/tiddlywebplugins.csrf
Author: Chris Dent
Author-email: cdent@peermore.com
License: UNKNOWN
Platform: Posix; MacOS X; Windows
